{
  "version": 1,
  "author": "Power Monitor",
  "editor": "wokwi",
  "parts": [
    {
      "type": "wokwi-esp32-devkit-v1",
      "id": "esp",
      "top": 300,
      "left": 420,
      "attrs": { "env": "arduino-cli" }
    },

    { "type": "wokwi-led", "id": "led_dr_l1", "top": 30,  "left": 30,  "attrs": { "color": "yellow", "label": "DR Light 1" } },
    { "type": "wokwi-led", "id": "led_dr_l2", "top": 30,  "left": 90,  "attrs": { "color": "yellow", "label": "DR Light 2" } },
    { "type": "wokwi-led", "id": "led_dr_l3", "top": 30,  "left": 150, "attrs": { "color": "yellow", "label": "DR Light 3" } },
    { "type": "wokwi-led", "id": "led_wr1_l1","top": 30,  "left": 240, "attrs": { "color": "yellow", "label": "WR1 Light 1" } },
    { "type": "wokwi-led", "id": "led_wr1_l2","top": 30,  "left": 300, "attrs": { "color": "yellow", "label": "WR1 Light 2" } },
    { "type": "wokwi-led", "id": "led_wr1_l3","top": 30,  "left": 360, "attrs": { "color": "yellow", "label": "WR1 Light 3" } },
    { "type": "wokwi-led", "id": "led_wr2_l1","top": 30,  "left": 450, "attrs": { "color": "yellow", "label": "WR2 Light 1" } },
    { "type": "wokwi-led", "id": "led_wr2_l2","top": 30,  "left": 510, "attrs": { "color": "yellow", "label": "WR2 Light 2" } },
    { "type": "wokwi-led", "id": "led_wr2_l3","top": 30,  "left": 570, "attrs": { "color": "yellow", "label": "WR2 Light 3" } },

    { "type": "wokwi-led", "id": "led_dr_f1", "top": 150, "left": 30,  "attrs": { "color": "blue",   "label": "DR Fan 1" } },
    { "type": "wokwi-led", "id": "led_dr_f2", "top": 150, "left": 90,  "attrs": { "color": "blue",   "label": "DR Fan 2" } },
    { "type": "wokwi-led", "id": "led_wr1_f1","top": 150, "left": 240, "attrs": { "color": "blue",   "label": "WR1 Fan 1" } },
    { "type": "wokwi-led", "id": "led_wr1_f2","top": 150, "left": 300, "attrs": { "color": "blue",   "label": "WR1 Fan 2" } },
    { "type": "wokwi-led", "id": "led_wr2_f1","top": 150, "left": 450, "attrs": { "color": "blue",   "label": "WR2 Fan 1" } },
    { "type": "wokwi-led", "id": "led_wr2_f2","top": 150, "left": 510, "attrs": { "color": "blue",   "label": "WR2 Fan 2" } },

    { "type": "wokwi-resistor", "id": "r1",  "top": 70,  "left": 30,  "attrs": { "value": "220" } },
    { "type": "wokwi-resistor", "id": "r2",  "top": 70,  "left": 90,  "attrs": { "value": "220" } },
    { "type": "wokwi-resistor", "id": "r3",  "top": 70,  "left": 150, "attrs": { "value": "220" } },
    { "type": "wokwi-resistor", "id": "r4",  "top": 70,  "left": 240, "attrs": { "value": "220" } },
    { "type": "wokwi-resistor", "id": "r5",  "top": 70,  "left": 300, "attrs": { "value": "220" } },
    { "type": "wokwi-resistor", "id": "r6",  "top": 70,  "left": 360, "attrs": { "value": "220" } },
    { "type": "wokwi-resistor", "id": "r7",  "top": 70,  "left": 450, "attrs": { "value": "220" } },
    { "type": "wokwi-resistor", "id": "r8",  "top": 70,  "left": 510, "attrs": { "value": "220" } },
    { "type": "wokwi-resistor", "id": "r9",  "top": 70,  "left": 570, "attrs": { "value": "220" } },
    { "type": "wokwi-resistor", "id": "r10", "top": 190, "left": 30,  "attrs": { "value": "220" } },
    { "type": "wokwi-resistor", "id": "r11", "top": 190, "left": 90,  "attrs": { "value": "220" } },
    { "type": "wokwi-resistor", "id": "r12", "top": 190, "left": 240, "attrs": { "value": "220" } },
    { "type": "wokwi-resistor", "id": "r13", "top": 190, "left": 300, "attrs": { "value": "220" } },
    { "type": "wokwi-resistor", "id": "r14", "top": 190, "left": 450, "attrs": { "value": "220" } },
    { "type": "wokwi-resistor", "id": "r15", "top": 190, "left": 510, "attrs": { "value": "220" } }
  ],
  "connections": [
    ["esp:D2",  "r1:1",  "green",  []],
    ["esp:D4",  "r2:1",  "green",  []],
    ["esp:D5",  "r3:1",  "green",  []],
    ["esp:D18", "r4:1",  "green",  []],
    ["esp:D19", "r5:1",  "green",  []],
    ["esp:D21", "r6:1",  "green",  []],
    ["esp:D22", "r7:1",  "green",  []],
    ["esp:D23", "r8:1",  "green",  []],
    ["esp:D25", "r9:1",  "green",  []],
    ["esp:D26", "r10:1", "blue",   []],
    ["esp:D27", "r11:1", "blue",   []],
    ["esp:D32", "r12:1", "blue",   []],
    ["esp:D33", "r13:1", "blue",   []],
    ["esp:D34", "r14:1", "blue",   []],
    ["esp:D35", "r15:1", "blue",   []],

    ["r1:2",  "led_dr_l1:A",  "green", []],
    ["r2:2",  "led_dr_l2:A",  "green", []],
    ["r3:2",  "led_dr_l3:A",  "green", []],
    ["r4:2",  "led_wr1_l1:A", "green", []],
    ["r5:2",  "led_wr1_l2:A", "green", []],
    ["r6:2",  "led_wr1_l3:A", "green", []],
    ["r7:2",  "led_wr2_l1:A", "green", []],
    ["r8:2",  "led_wr2_l2:A", "green", []],
    ["r9:2",  "led_wr2_l3:A", "green", []],
    ["r10:2", "led_dr_f1:A",  "blue",  []],
    ["r11:2", "led_dr_f2:A",  "blue",  []],
    ["r12:2", "led_wr1_f1:A", "blue",  []],
    ["r13:2", "led_wr1_f2:A", "blue",  []],
    ["r14:2", "led_wr2_f1:A", "blue",  []],
    ["r15:2", "led_wr2_f2:A", "blue",  []],

    ["led_dr_l1:C",  "esp:GND.1", "black", []],
    ["led_dr_l2:C",  "esp:GND.1", "black", []],
    ["led_dr_l3:C",  "esp:GND.1", "black", []],
    ["led_wr1_l1:C", "esp:GND.1", "black", []],
    ["led_wr1_l2:C", "esp:GND.1", "black", []],
    ["led_wr1_l3:C", "esp:GND.1", "black", []],
    ["led_wr2_l1:C", "esp:GND.1", "black", []],
    ["led_wr2_l2:C", "esp:GND.1", "black", []],
    ["led_wr2_l3:C", "esp:GND.1", "black", []],
    ["led_dr_f1:C",  "esp:GND.2", "black", []],
    ["led_dr_f2:C",  "esp:GND.2", "black", []],
    ["led_wr1_f1:C", "esp:GND.2", "black", []],
    ["led_wr1_f2:C", "esp:GND.2", "black", []],
    ["led_wr2_f1:C", "esp:GND.2", "black", []],
    ["led_wr2_f2:C", "esp:GND.2", "black", []],

    ["esp:3V3", "esp:GND.1", "red", []]
  ]
}
